rnftools/__init__.py
rnftools/include_all.snake
rnftools/scripts.py
rnftools/version.py
rnftools/lavender/Bam.py
rnftools/lavender/Panel.py
rnftools/lavender/Report.py
rnftools/lavender/__init__.py
rnftools/lavender/lavender.snake
rnftools/mishmash/ArtIllumina.py
rnftools/mishmash/CuReSim.py
rnftools/mishmash/DwgSim.py
rnftools/mishmash/MasonIllumina.py
rnftools/mishmash/Sample.py
rnftools/mishmash/Source.py
rnftools/mishmash/WgSim.py
rnftools/mishmash/__init__.py
rnftools/mishmash/mishmash.snake
rnftools/rnfformat/FqCreator.py
rnftools/rnfformat/FqMerger.py
rnftools/rnfformat/ReadTuple.py
rnftools/rnfformat/RnfLifter.py
rnftools/rnfformat/RnfProfile.py
rnftools/rnfformat/Segment.py
rnftools/rnfformat/Validator.py
rnftools/rnfformat/__init__.py
rnftools/utils/Chain.py
rnftools/utils/ChainSequence.py
rnftools/utils/FaIdx.py
rnftools/utils/__init__.py
rnftools-0.4.0.0.dist-info/LICENSE
rnftools-0.4.0.0.dist-info/METADATA
rnftools-0.4.0.0.dist-info/WHEEL
rnftools-0.4.0.0.dist-info/entry_points.txt
rnftools-0.4.0.0.dist-info/top_level.txt
rnftools-0.4.0.0.dist-info/RECORD
