Metadata-Version: 2.1
Name: rnftools
Version: 0.4.0.0
Summary: RNF framework for NGS: simulation of reads, evaluation of mappers, conversion of RNF-compliant data.
Home-page: http://karel-brinda.github.io/rnftools/
Author: Karel Brinda
Author-email: karel.brinda@univ-mlv.fr
License: MIT
Keywords: Bioinformatics,Computational Biology,Next-Generation Sequencing,Read Simulation,Mappers Evaluation
Classifier: Development Status :: 5 - Production/Stable
Classifier: Environment :: Console
Classifier: Intended Audience :: Science/Research
Classifier: License :: OSI Approved :: MIT License
Classifier: Natural Language :: English
Classifier: Programming Language :: Python :: 3 :: Only
Classifier: Operating System :: Unix
Classifier: Topic :: Scientific/Engineering :: Bio-Informatics
License-File: LICENSE
Requires-Dist: argparse
Requires-Dist: beautifulsoup4
Requires-Dist: pyfaidx
Requires-Dist: pysam
Requires-Dist: snakemake
Requires-Dist: svg42pdf>=0.1.1
